{
  "clazz" : "org.apache.catalina.realm.TestJNDIRealm",
  "methods" : [ {
    "method" : "testErrorRealm",
    "datacollectorResults" : [ {
      "name" : "de.dagere.kopeme.datacollection.TimeDataCollectorNoGC",
      "chunks" : [ ],
      "results" : [ {
        "value" : 1.4782399388125008E8,
        "deviation" : 0.3988112166699464,
        "min" : 8.9613157E7,
        "max" : 6.54814481E8,
        "warmup" : 0,
        "iterations" : 160,
        "repetitions" : 100,
        "commit" : null,
        "vmRunConfiguration" : {
          "showStart" : false,
          "executeBeforeClassInMeasurement" : false,
          "redirectToTemp" : false,
          "redirectToNull" : true,
          "useKieker" : false
        },
        "javaVersion" : "11.0.16",
        "cpu" : "model name : Intel(R) Core(TM) i7-4770 CPU @ 3.40GHz",
        "memory" : "MemTotal: 16280676 kB",
        "date" : 1671510131723,
        "fulldata" : {
          "fileName" : null,
          "values" : [ {
            "startTime" : 1671510107965,
            "value" : 654814481
          }, {
            "startTime" : 1671510108620,
            "value" : 248455861
          }, {
            "startTime" : 1671510108869,
            "value" : 269238750
          }, {
            "startTime" : 1671510109138,
            "value" : 267382299
          }, {
            "startTime" : 1671510109405,
            "value" : 251153772
          }, {
            "startTime" : 1671510109657,
            "value" : 195488356
          }, {
            "startTime" : 1671510109852,
            "value" : 171153843
          }, {
            "startTime" : 1671510110023,
            "value" : 175831399
          }, {
            "startTime" : 1671510110199,
            "value" : 144218685
          }, {
            "startTime" : 1671510110344,
            "value" : 114537193
          }, {
            "startTime" : 1671510110458,
            "value" : 133543255
          }, {
            "startTime" : 1671510110592,
            "value" : 149062787
          }, {
            "startTime" : 1671510110741,
            "value" : 261970339
          }, {
            "startTime" : 1671510111003,
            "value" : 230430018
          }, {
            "startTime" : 1671510111233,
            "value" : 182848067
          }, {
            "startTime" : 1671510111416,
            "value" : 118742810
          }, {
            "startTime" : 1671510111535,
            "value" : 208460754
          }, {
            "startTime" : 1671510111744,
            "value" : 162550166
          }, {
            "startTime" : 1671510111906,
            "value" : 131468101
          }, {
            "startTime" : 1671510112038,
            "value" : 203482905
          }, {
            "startTime" : 1671510112241,
            "value" : 113336479
          }, {
            "startTime" : 1671510112355,
            "value" : 177646943
          }, {
            "startTime" : 1671510112532,
            "value" : 113722465
          }, {
            "startTime" : 1671510112646,
            "value" : 108655150
          }, {
            "startTime" : 1671510112755,
            "value" : 133618282
          }, {
            "startTime" : 1671510112888,
            "value" : 143599150
          }, {
            "startTime" : 1671510113032,
            "value" : 130755922
          }, {
            "startTime" : 1671510113163,
            "value" : 132387158
          }, {
            "startTime" : 1671510113295,
            "value" : 139783110
          }, {
            "startTime" : 1671510113435,
            "value" : 132806795
          }, {
            "startTime" : 1671510113568,
            "value" : 150258890
          }, {
            "startTime" : 1671510113718,
            "value" : 140803806
          }, {
            "startTime" : 1671510113859,
            "value" : 143160528
          }, {
            "startTime" : 1671510114002,
            "value" : 139215792
          }, {
            "startTime" : 1671510114142,
            "value" : 145978197
          }, {
            "startTime" : 1671510114288,
            "value" : 143638691
          }, {
            "startTime" : 1671510114431,
            "value" : 144569971
          }, {
            "startTime" : 1671510114576,
            "value" : 144926183
          }, {
            "startTime" : 1671510114721,
            "value" : 148831800
          }, {
            "startTime" : 1671510114870,
            "value" : 135588088
          }, {
            "startTime" : 1671510115006,
            "value" : 141129852
          }, {
            "startTime" : 1671510115147,
            "value" : 140409448
          }, {
            "startTime" : 1671510115287,
            "value" : 145743963
          }, {
            "startTime" : 1671510115433,
            "value" : 144773129
          }, {
            "startTime" : 1671510115578,
            "value" : 140817596
          }, {
            "startTime" : 1671510115719,
            "value" : 148487094
          }, {
            "startTime" : 1671510115867,
            "value" : 143002922
          }, {
            "startTime" : 1671510116010,
            "value" : 133495027
          }, {
            "startTime" : 1671510116144,
            "value" : 116047299
          }, {
            "startTime" : 1671510116260,
            "value" : 104963361
          }, {
            "startTime" : 1671510116365,
            "value" : 94948233
          }, {
            "startTime" : 1671510116460,
            "value" : 105206954
          }, {
            "startTime" : 1671510116565,
            "value" : 96140351
          }, {
            "startTime" : 1671510116661,
            "value" : 126346704
          }, {
            "startTime" : 1671510116788,
            "value" : 89613157
          }, {
            "startTime" : 1671510116877,
            "value" : 94597160
          }, {
            "startTime" : 1671510116972,
            "value" : 125733560
          }, {
            "startTime" : 1671510117098,
            "value" : 115542767
          }, {
            "startTime" : 1671510117213,
            "value" : 148714478
          }, {
            "startTime" : 1671510117362,
            "value" : 128954990
          }, {
            "startTime" : 1671510117491,
            "value" : 125198225
          }, {
            "startTime" : 1671510117616,
            "value" : 123199910
          }, {
            "startTime" : 1671510117740,
            "value" : 141627959
          }, {
            "startTime" : 1671510117881,
            "value" : 139653792
          }, {
            "startTime" : 1671510118021,
            "value" : 101308694
          }, {
            "startTime" : 1671510118122,
            "value" : 91101902
          }, {
            "startTime" : 1671510118214,
            "value" : 93165598
          }, {
            "startTime" : 1671510118307,
            "value" : 96887996
          }, {
            "startTime" : 1671510118404,
            "value" : 99375953
          }, {
            "startTime" : 1671510118503,
            "value" : 101088998
          }, {
            "startTime" : 1671510118604,
            "value" : 94794716
          }, {
            "startTime" : 1671510118699,
            "value" : 132923744
          }, {
            "startTime" : 1671510118832,
            "value" : 103095772
          }, {
            "startTime" : 1671510118935,
            "value" : 140635957
          }, {
            "startTime" : 1671510119076,
            "value" : 140547257
          }, {
            "startTime" : 1671510119217,
            "value" : 131089911
          }, {
            "startTime" : 1671510119348,
            "value" : 132578737
          }, {
            "startTime" : 1671510119480,
            "value" : 132577705
          }, {
            "startTime" : 1671510119613,
            "value" : 141074429
          }, {
            "startTime" : 1671510119754,
            "value" : 139895420
          }, {
            "startTime" : 1671510119894,
            "value" : 146350513
          }, {
            "startTime" : 1671510120040,
            "value" : 142705456
          }, {
            "startTime" : 1671510120183,
            "value" : 143028029
          }, {
            "startTime" : 1671510120326,
            "value" : 137882248
          }, {
            "startTime" : 1671510120464,
            "value" : 146054641
          }, {
            "startTime" : 1671510120610,
            "value" : 151276662
          }, {
            "startTime" : 1671510120762,
            "value" : 141101113
          }, {
            "startTime" : 1671510120903,
            "value" : 146940567
          }, {
            "startTime" : 1671510121050,
            "value" : 136711939
          }, {
            "startTime" : 1671510121187,
            "value" : 141152707
          }, {
            "startTime" : 1671510121328,
            "value" : 145787939
          }, {
            "startTime" : 1671510121474,
            "value" : 141522761
          }, {
            "startTime" : 1671510121615,
            "value" : 135559960
          }, {
            "startTime" : 1671510121751,
            "value" : 123506098
          }, {
            "startTime" : 1671510121874,
            "value" : 135723983
          }, {
            "startTime" : 1671510122010,
            "value" : 137494978
          }, {
            "startTime" : 1671510122148,
            "value" : 134295390
          }, {
            "startTime" : 1671510122282,
            "value" : 140280531
          }, {
            "startTime" : 1671510122422,
            "value" : 145057544
          }, {
            "startTime" : 1671510122568,
            "value" : 138045717
          }, {
            "startTime" : 1671510122706,
            "value" : 131745931
          }, {
            "startTime" : 1671510122837,
            "value" : 135845498
          }, {
            "startTime" : 1671510122973,
            "value" : 145193494
          }, {
            "startTime" : 1671510123119,
            "value" : 139994432
          }, {
            "startTime" : 1671510123259,
            "value" : 139989813
          }, {
            "startTime" : 1671510123399,
            "value" : 131155861
          }, {
            "startTime" : 1671510123530,
            "value" : 137199518
          }, {
            "startTime" : 1671510123667,
            "value" : 144480677
          }, {
            "startTime" : 1671510123812,
            "value" : 133119840
          }, {
            "startTime" : 1671510123945,
            "value" : 142046955
          }, {
            "startTime" : 1671510124087,
            "value" : 143404195
          }, {
            "startTime" : 1671510124230,
            "value" : 138764193
          }, {
            "startTime" : 1671510124369,
            "value" : 138969839
          }, {
            "startTime" : 1671510124508,
            "value" : 147122885
          }, {
            "startTime" : 1671510124655,
            "value" : 137653791
          }, {
            "startTime" : 1671510124793,
            "value" : 140757051
          }, {
            "startTime" : 1671510124934,
            "value" : 145943740
          }, {
            "startTime" : 1671510125080,
            "value" : 140607697
          }, {
            "startTime" : 1671510125221,
            "value" : 153912748
          }, {
            "startTime" : 1671510125375,
            "value" : 139985827
          }, {
            "startTime" : 1671510125515,
            "value" : 141933343
          }, {
            "startTime" : 1671510125657,
            "value" : 143802768
          }, {
            "startTime" : 1671510125800,
            "value" : 136847572
          }, {
            "startTime" : 1671510125937,
            "value" : 141528225
          }, {
            "startTime" : 1671510126079,
            "value" : 145529793
          }, {
            "startTime" : 1671510126225,
            "value" : 137899866
          }, {
            "startTime" : 1671510126363,
            "value" : 133664197
          }, {
            "startTime" : 1671510126496,
            "value" : 134147126
          }, {
            "startTime" : 1671510126630,
            "value" : 136637105
          }, {
            "startTime" : 1671510126767,
            "value" : 139848219
          }, {
            "startTime" : 1671510126907,
            "value" : 133985631
          }, {
            "startTime" : 1671510127041,
            "value" : 123235982
          }, {
            "startTime" : 1671510127164,
            "value" : 139561146
          }, {
            "startTime" : 1671510127304,
            "value" : 134644992
          }, {
            "startTime" : 1671510127439,
            "value" : 130578267
          }, {
            "startTime" : 1671510127569,
            "value" : 141877640
          }, {
            "startTime" : 1671510127711,
            "value" : 130379706
          }, {
            "startTime" : 1671510127842,
            "value" : 134056095
          }, {
            "startTime" : 1671510127976,
            "value" : 147466030
          }, {
            "startTime" : 1671510128123,
            "value" : 143644801
          }, {
            "startTime" : 1671510128267,
            "value" : 142758127
          }, {
            "startTime" : 1671510128410,
            "value" : 141033122
          }, {
            "startTime" : 1671510128551,
            "value" : 142746163
          }, {
            "startTime" : 1671510128694,
            "value" : 134363943
          }, {
            "startTime" : 1671510128828,
            "value" : 139528413
          }, {
            "startTime" : 1671510128968,
            "value" : 138839136
          }, {
            "startTime" : 1671510129106,
            "value" : 144066518
          }, {
            "startTime" : 1671510129251,
            "value" : 135579940
          }, {
            "startTime" : 1671510129386,
            "value" : 139435952
          }, {
            "startTime" : 1671510129526,
            "value" : 143555847
          }, {
            "startTime" : 1671510129669,
            "value" : 137844856
          }, {
            "startTime" : 1671510129807,
            "value" : 142842571
          }, {
            "startTime" : 1671510129950,
            "value" : 140758976
          }, {
            "startTime" : 1671510130091,
            "value" : 139853534
          }, {
            "startTime" : 1671510130231,
            "value" : 142916545
          }, {
            "startTime" : 1671510130374,
            "value" : 140206792
          }, {
            "startTime" : 1671510130514,
            "value" : 535409676
          }, {
            "startTime" : 1671510131049,
            "value" : 177201186
          }, {
            "startTime" : 1671510131227,
            "value" : 205141063
          }, {
            "startTime" : 1671510131432,
            "value" : 193507435
          } ]
        }
      } ]
    } ]
  } ]
}