{
  "clazz" : "org.apache.el.parser.TestAstLambdaExpression",
  "methods" : [ {
    "method" : "testSpec05",
    "datacollectorResults" : [ {
      "name" : "de.dagere.kopeme.datacollection.TimeDataCollectorNoGC",
      "chunks" : [ ],
      "results" : [ {
        "value" : 2736168.4312500004,
        "deviation" : 1.6731493429634594,
        "min" : 1767098.0,
        "max" : 5.7547772E7,
        "warmup" : 0,
        "iterations" : 160,
        "repetitions" : 100,
        "commit" : null,
        "vmRunConfiguration" : {
          "showStart" : false,
          "executeBeforeClassInMeasurement" : false,
          "redirectToTemp" : false,
          "redirectToNull" : true,
          "useKieker" : false
        },
        "javaVersion" : "11.0.16",
        "cpu" : "model name : Intel(R) Core(TM) i7-4770 CPU @ 3.40GHz",
        "memory" : "MemTotal: 16280676 kB",
        "date" : 1672372747108,
        "fulldata" : {
          "fileName" : null,
          "values" : [ {
            "startTime" : 1672372746488,
            "value" : 57547772
          }, {
            "startTime" : 1672372746546,
            "value" : 14332191
          }, {
            "startTime" : 1672372746560,
            "value" : 10053667
          }, {
            "startTime" : 1672372746571,
            "value" : 7307932
          }, {
            "startTime" : 1672372746578,
            "value" : 6597572
          }, {
            "startTime" : 1672372746585,
            "value" : 5925366
          }, {
            "startTime" : 1672372746591,
            "value" : 5275301
          }, {
            "startTime" : 1672372746596,
            "value" : 4998423
          }, {
            "startTime" : 1672372746601,
            "value" : 3830722
          }, {
            "startTime" : 1672372746605,
            "value" : 3558588
          }, {
            "startTime" : 1672372746608,
            "value" : 3356721
          }, {
            "startTime" : 1672372746612,
            "value" : 4050370
          }, {
            "startTime" : 1672372746616,
            "value" : 2692580
          }, {
            "startTime" : 1672372746619,
            "value" : 2596236
          }, {
            "startTime" : 1672372746621,
            "value" : 3037825
          }, {
            "startTime" : 1672372746624,
            "value" : 2884767
          }, {
            "startTime" : 1672372746627,
            "value" : 2745045
          }, {
            "startTime" : 1672372746630,
            "value" : 2779290
          }, {
            "startTime" : 1672372746633,
            "value" : 2725017
          }, {
            "startTime" : 1672372746636,
            "value" : 2746517
          }, {
            "startTime" : 1672372746638,
            "value" : 2659456
          }, {
            "startTime" : 1672372746641,
            "value" : 2721869
          }, {
            "startTime" : 1672372746644,
            "value" : 2437109
          }, {
            "startTime" : 1672372746646,
            "value" : 2546143
          }, {
            "startTime" : 1672372746649,
            "value" : 2629038
          }, {
            "startTime" : 1672372746652,
            "value" : 2601632
          }, {
            "startTime" : 1672372746654,
            "value" : 3201009
          }, {
            "startTime" : 1672372746657,
            "value" : 2330041
          }, {
            "startTime" : 1672372746660,
            "value" : 2394463
          }, {
            "startTime" : 1672372746662,
            "value" : 2349747
          }, {
            "startTime" : 1672372746665,
            "value" : 2279441
          }, {
            "startTime" : 1672372746667,
            "value" : 2161096
          }, {
            "startTime" : 1672372746669,
            "value" : 2030345
          }, {
            "startTime" : 1672372746671,
            "value" : 2043729
          }, {
            "startTime" : 1672372746673,
            "value" : 2143167
          }, {
            "startTime" : 1672372746676,
            "value" : 2131017
          }, {
            "startTime" : 1672372746678,
            "value" : 2140252
          }, {
            "startTime" : 1672372746680,
            "value" : 2102851
          }, {
            "startTime" : 1672372746682,
            "value" : 2118728
          }, {
            "startTime" : 1672372746684,
            "value" : 2141235
          }, {
            "startTime" : 1672372746686,
            "value" : 2073984
          }, {
            "startTime" : 1672372746689,
            "value" : 2016914
          }, {
            "startTime" : 1672372746691,
            "value" : 2136423
          }, {
            "startTime" : 1672372746693,
            "value" : 2975525
          }, {
            "startTime" : 1672372746696,
            "value" : 2024916
          }, {
            "startTime" : 1672372746698,
            "value" : 1892896
          }, {
            "startTime" : 1672372746700,
            "value" : 1885439
          }, {
            "startTime" : 1672372746702,
            "value" : 1944228
          }, {
            "startTime" : 1672372746704,
            "value" : 2070262
          }, {
            "startTime" : 1672372746706,
            "value" : 1926116
          }, {
            "startTime" : 1672372746708,
            "value" : 1914622
          }, {
            "startTime" : 1672372746710,
            "value" : 1917856
          }, {
            "startTime" : 1672372746712,
            "value" : 1878557
          }, {
            "startTime" : 1672372746714,
            "value" : 1879744
          }, {
            "startTime" : 1672372746716,
            "value" : 1880859
          }, {
            "startTime" : 1672372746718,
            "value" : 1908949
          }, {
            "startTime" : 1672372746720,
            "value" : 1924045
          }, {
            "startTime" : 1672372746722,
            "value" : 1938928
          }, {
            "startTime" : 1672372746724,
            "value" : 1924922
          }, {
            "startTime" : 1672372746726,
            "value" : 1922541
          }, {
            "startTime" : 1672372746728,
            "value" : 3035350
          }, {
            "startTime" : 1672372746731,
            "value" : 1878228
          }, {
            "startTime" : 1672372746733,
            "value" : 1852487
          }, {
            "startTime" : 1672372746735,
            "value" : 1881526
          }, {
            "startTime" : 1672372746737,
            "value" : 1876386
          }, {
            "startTime" : 1672372746739,
            "value" : 1859059
          }, {
            "startTime" : 1672372746740,
            "value" : 1881019
          }, {
            "startTime" : 1672372746742,
            "value" : 1962550
          }, {
            "startTime" : 1672372746744,
            "value" : 2033571
          }, {
            "startTime" : 1672372746746,
            "value" : 2043970
          }, {
            "startTime" : 1672372746749,
            "value" : 2025439
          }, {
            "startTime" : 1672372746751,
            "value" : 2008806
          }, {
            "startTime" : 1672372746753,
            "value" : 2020858
          }, {
            "startTime" : 1672372746755,
            "value" : 2002380
          }, {
            "startTime" : 1672372746757,
            "value" : 2033069
          }, {
            "startTime" : 1672372746759,
            "value" : 1931022
          }, {
            "startTime" : 1672372746761,
            "value" : 1940486
          }, {
            "startTime" : 1672372746763,
            "value" : 2728229
          }, {
            "startTime" : 1672372746766,
            "value" : 1794631
          }, {
            "startTime" : 1672372746767,
            "value" : 1867578
          }, {
            "startTime" : 1672372746769,
            "value" : 1928880
          }, {
            "startTime" : 1672372746771,
            "value" : 1874806
          }, {
            "startTime" : 1672372746773,
            "value" : 2040311
          }, {
            "startTime" : 1672372746775,
            "value" : 1983395
          }, {
            "startTime" : 1672372746777,
            "value" : 2063491
          }, {
            "startTime" : 1672372746779,
            "value" : 1971201
          }, {
            "startTime" : 1672372746781,
            "value" : 2064846
          }, {
            "startTime" : 1672372746784,
            "value" : 2039826
          }, {
            "startTime" : 1672372746786,
            "value" : 2022577
          }, {
            "startTime" : 1672372746788,
            "value" : 1933099
          }, {
            "startTime" : 1672372746790,
            "value" : 1930333
          }, {
            "startTime" : 1672372746792,
            "value" : 1877577
          }, {
            "startTime" : 1672372746794,
            "value" : 1849330
          }, {
            "startTime" : 1672372746795,
            "value" : 1973968
          }, {
            "startTime" : 1672372746797,
            "value" : 1962958
          }, {
            "startTime" : 1672372746799,
            "value" : 2351295
          }, {
            "startTime" : 1672372746802,
            "value" : 3100190
          }, {
            "startTime" : 1672372746805,
            "value" : 2025149
          }, {
            "startTime" : 1672372746807,
            "value" : 2026420
          }, {
            "startTime" : 1672372746809,
            "value" : 2049265
          }, {
            "startTime" : 1672372746811,
            "value" : 2051515
          }, {
            "startTime" : 1672372746813,
            "value" : 1964540
          }, {
            "startTime" : 1672372746815,
            "value" : 1915635
          }, {
            "startTime" : 1672372746817,
            "value" : 1864945
          }, {
            "startTime" : 1672372746819,
            "value" : 1904538
          }, {
            "startTime" : 1672372746821,
            "value" : 1888002
          }, {
            "startTime" : 1672372746823,
            "value" : 1916685
          }, {
            "startTime" : 1672372746825,
            "value" : 1808347
          }, {
            "startTime" : 1672372746827,
            "value" : 1878806
          }, {
            "startTime" : 1672372746829,
            "value" : 1808263
          }, {
            "startTime" : 1672372746831,
            "value" : 1981061
          }, {
            "startTime" : 1672372746833,
            "value" : 1970957
          }, {
            "startTime" : 1672372746835,
            "value" : 1946947
          }, {
            "startTime" : 1672372746837,
            "value" : 1966232
          }, {
            "startTime" : 1672372746839,
            "value" : 3936548
          }, {
            "startTime" : 1672372746843,
            "value" : 2011155
          }, {
            "startTime" : 1672372746845,
            "value" : 1981733
          }, {
            "startTime" : 1672372746847,
            "value" : 1940288
          }, {
            "startTime" : 1672372746849,
            "value" : 1860788
          }, {
            "startTime" : 1672372746851,
            "value" : 1805896
          }, {
            "startTime" : 1672372746853,
            "value" : 1808616
          }, {
            "startTime" : 1672372746854,
            "value" : 1876633
          }, {
            "startTime" : 1672372746857,
            "value" : 1959145
          }, {
            "startTime" : 1672372746859,
            "value" : 1958768
          }, {
            "startTime" : 1672372746861,
            "value" : 2022727
          }, {
            "startTime" : 1672372746863,
            "value" : 1953128
          }, {
            "startTime" : 1672372746866,
            "value" : 2019578
          }, {
            "startTime" : 1672372746868,
            "value" : 2075190
          }, {
            "startTime" : 1672372746872,
            "value" : 2028407
          }, {
            "startTime" : 1672372746874,
            "value" : 1864326
          }, {
            "startTime" : 1672372746876,
            "value" : 1823737
          }, {
            "startTime" : 1672372746878,
            "value" : 1781220
          }, {
            "startTime" : 1672372746880,
            "value" : 3258176
          }, {
            "startTime" : 1672372746883,
            "value" : 1963490
          }, {
            "startTime" : 1672372746885,
            "value" : 1974432
          }, {
            "startTime" : 1672372746887,
            "value" : 1980036
          }, {
            "startTime" : 1672372746889,
            "value" : 1997735
          }, {
            "startTime" : 1672372746891,
            "value" : 1992235
          }, {
            "startTime" : 1672372746893,
            "value" : 1981160
          }, {
            "startTime" : 1672372746895,
            "value" : 1984857
          }, {
            "startTime" : 1672372746897,
            "value" : 1921766
          }, {
            "startTime" : 1672372746899,
            "value" : 1887790
          }, {
            "startTime" : 1672372746901,
            "value" : 1886491
          }, {
            "startTime" : 1672372746903,
            "value" : 1767098
          }, {
            "startTime" : 1672372746905,
            "value" : 1956193
          }, {
            "startTime" : 1672372746907,
            "value" : 1905386
          }, {
            "startTime" : 1672372746909,
            "value" : 1911668
          }, {
            "startTime" : 1672372746911,
            "value" : 1967176
          }, {
            "startTime" : 1672372746913,
            "value" : 1991950
          }, {
            "startTime" : 1672372746915,
            "value" : 1959704
          }, {
            "startTime" : 1672372746917,
            "value" : 1883276
          }, {
            "startTime" : 1672372746918,
            "value" : 2932489
          }, {
            "startTime" : 1672372746921,
            "value" : 2025702
          }, {
            "startTime" : 1672372746923,
            "value" : 1894239
          }, {
            "startTime" : 1672372746925,
            "value" : 1935527
          }, {
            "startTime" : 1672372746927,
            "value" : 1850429
          }, {
            "startTime" : 1672372746929,
            "value" : 1828576
          }, {
            "startTime" : 1672372746931,
            "value" : 1797706
          }, {
            "startTime" : 1672372746933,
            "value" : 1932569
          }, {
            "startTime" : 1672372746935,
            "value" : 1877180
          } ]
        }
      } ]
    } ]
  } ]
}