{
  "clazz" : "org.apache.el.lang.TestELArithmetic",
  "methods" : [ {
    "method" : "testBug47371bigInteger",
    "datacollectorResults" : [ {
      "name" : "de.dagere.kopeme.datacollection.TimeDataCollectorNoGC",
      "chunks" : [ ],
      "results" : [ {
        "value" : 117062.38750000013,
        "deviation" : 2.5688229165049967,
        "min" : 37440.0,
        "max" : 3674055.0,
        "warmup" : 0,
        "iterations" : 160,
        "repetitions" : 100,
        "commit" : null,
        "vmRunConfiguration" : {
          "showStart" : false,
          "executeBeforeClassInMeasurement" : false,
          "redirectToTemp" : false,
          "redirectToNull" : true,
          "useKieker" : false
        },
        "javaVersion" : "11.0.17",
        "cpu" : "model name : Intel(R) Core(TM) i7-6700 CPU @ 3.40GHz",
        "memory" : "MemTotal: 16275336 kB",
        "date" : 1671704466465,
        "fulldata" : {
          "fileName" : null,
          "values" : [ {
            "startTime" : 1671704466226,
            "value" : 3674055
          }, {
            "startTime" : 1671704466230,
            "value" : 636249
          }, {
            "startTime" : 1671704466231,
            "value" : 621449
          }, {
            "startTime" : 1671704466231,
            "value" : 509834
          }, {
            "startTime" : 1671704466232,
            "value" : 426577
          }, {
            "startTime" : 1671704466232,
            "value" : 452750
          }, {
            "startTime" : 1671704466233,
            "value" : 402541
          }, {
            "startTime" : 1671704466233,
            "value" : 405191
          }, {
            "startTime" : 1671704466234,
            "value" : 341704
          }, {
            "startTime" : 1671704466234,
            "value" : 331939
          }, {
            "startTime" : 1671704466234,
            "value" : 253660
          }, {
            "startTime" : 1671704466235,
            "value" : 254555
          }, {
            "startTime" : 1671704466235,
            "value" : 267094
          }, {
            "startTime" : 1671704466235,
            "value" : 248370
          }, {
            "startTime" : 1671704466235,
            "value" : 195783
          }, {
            "startTime" : 1671704466236,
            "value" : 196993
          }, {
            "startTime" : 1671704466236,
            "value" : 206050
          }, {
            "startTime" : 1671704466236,
            "value" : 172389
          }, {
            "startTime" : 1671704466236,
            "value" : 165436
          }, {
            "startTime" : 1671704466236,
            "value" : 170574
          }, {
            "startTime" : 1671704466237,
            "value" : 138584
          }, {
            "startTime" : 1671704466237,
            "value" : 133497
          }, {
            "startTime" : 1671704466237,
            "value" : 75408
          }, {
            "startTime" : 1671704466237,
            "value" : 75782
          }, {
            "startTime" : 1671704466237,
            "value" : 87029
          }, {
            "startTime" : 1671704466237,
            "value" : 76395
          }, {
            "startTime" : 1671704466237,
            "value" : 85923
          }, {
            "startTime" : 1671704466237,
            "value" : 109063
          }, {
            "startTime" : 1671704466238,
            "value" : 107664
          }, {
            "startTime" : 1671704466238,
            "value" : 102107
          }, {
            "startTime" : 1671704466238,
            "value" : 110125
          }, {
            "startTime" : 1671704466238,
            "value" : 106876
          }, {
            "startTime" : 1671704466238,
            "value" : 99752
          }, {
            "startTime" : 1671704466238,
            "value" : 119225
          }, {
            "startTime" : 1671704466238,
            "value" : 80022
          }, {
            "startTime" : 1671704466238,
            "value" : 88406
          }, {
            "startTime" : 1671704466238,
            "value" : 77763
          }, {
            "startTime" : 1671704466239,
            "value" : 83401
          }, {
            "startTime" : 1671704466239,
            "value" : 93056
          }, {
            "startTime" : 1671704466239,
            "value" : 78458
          }, {
            "startTime" : 1671704466239,
            "value" : 81320
          }, {
            "startTime" : 1671704466239,
            "value" : 79337
          }, {
            "startTime" : 1671704466239,
            "value" : 91241
          }, {
            "startTime" : 1671704466239,
            "value" : 84576
          }, {
            "startTime" : 1671704466239,
            "value" : 81978
          }, {
            "startTime" : 1671704466239,
            "value" : 84589
          }, {
            "startTime" : 1671704466239,
            "value" : 80212
          }, {
            "startTime" : 1671704466240,
            "value" : 85489
          }, {
            "startTime" : 1671704466240,
            "value" : 85674
          }, {
            "startTime" : 1671704466240,
            "value" : 80153
          }, {
            "startTime" : 1671704466240,
            "value" : 83568
          }, {
            "startTime" : 1671704466240,
            "value" : 82493
          }, {
            "startTime" : 1671704466240,
            "value" : 82655
          }, {
            "startTime" : 1671704466240,
            "value" : 91234
          }, {
            "startTime" : 1671704466240,
            "value" : 87033
          }, {
            "startTime" : 1671704466240,
            "value" : 71202
          }, {
            "startTime" : 1671704466241,
            "value" : 73194
          }, {
            "startTime" : 1671704466241,
            "value" : 68255
          }, {
            "startTime" : 1671704466241,
            "value" : 62586
          }, {
            "startTime" : 1671704466241,
            "value" : 63474
          }, {
            "startTime" : 1671704466241,
            "value" : 58826
          }, {
            "startTime" : 1671704466241,
            "value" : 73021
          }, {
            "startTime" : 1671704466241,
            "value" : 59482
          }, {
            "startTime" : 1671704466241,
            "value" : 65249
          }, {
            "startTime" : 1671704466241,
            "value" : 81164
          }, {
            "startTime" : 1671704466241,
            "value" : 68667
          }, {
            "startTime" : 1671704466241,
            "value" : 74726
          }, {
            "startTime" : 1671704466241,
            "value" : 63804
          }, {
            "startTime" : 1671704466242,
            "value" : 63905
          }, {
            "startTime" : 1671704466242,
            "value" : 67109
          }, {
            "startTime" : 1671704466242,
            "value" : 65679
          }, {
            "startTime" : 1671704466242,
            "value" : 64783
          }, {
            "startTime" : 1671704466242,
            "value" : 64022
          }, {
            "startTime" : 1671704466242,
            "value" : 67683
          }, {
            "startTime" : 1671704466242,
            "value" : 67343
          }, {
            "startTime" : 1671704466242,
            "value" : 83145
          }, {
            "startTime" : 1671704466242,
            "value" : 71356
          }, {
            "startTime" : 1671704466242,
            "value" : 65569
          }, {
            "startTime" : 1671704466242,
            "value" : 69241
          }, {
            "startTime" : 1671704466242,
            "value" : 60241
          }, {
            "startTime" : 1671704466242,
            "value" : 59292
          }, {
            "startTime" : 1671704466243,
            "value" : 64242
          }, {
            "startTime" : 1671704466243,
            "value" : 62125
          }, {
            "startTime" : 1671704466243,
            "value" : 73870
          }, {
            "startTime" : 1671704466243,
            "value" : 53743
          }, {
            "startTime" : 1671704466243,
            "value" : 85003
          }, {
            "startTime" : 1671704466243,
            "value" : 53192
          }, {
            "startTime" : 1671704466243,
            "value" : 68844
          }, {
            "startTime" : 1671704466243,
            "value" : 57424
          }, {
            "startTime" : 1671704466243,
            "value" : 53819
          }, {
            "startTime" : 1671704466243,
            "value" : 47807
          }, {
            "startTime" : 1671704466243,
            "value" : 48198
          }, {
            "startTime" : 1671704466243,
            "value" : 50998
          }, {
            "startTime" : 1671704466243,
            "value" : 49962
          }, {
            "startTime" : 1671704466243,
            "value" : 60878
          }, {
            "startTime" : 1671704466244,
            "value" : 54753
          }, {
            "startTime" : 1671704466244,
            "value" : 56943
          }, {
            "startTime" : 1671704466244,
            "value" : 81835
          }, {
            "startTime" : 1671704466244,
            "value" : 48954
          }, {
            "startTime" : 1671704466244,
            "value" : 50422
          }, {
            "startTime" : 1671704466244,
            "value" : 47715
          }, {
            "startTime" : 1671704466244,
            "value" : 45924
          }, {
            "startTime" : 1671704466244,
            "value" : 50149
          }, {
            "startTime" : 1671704466244,
            "value" : 51513
          }, {
            "startTime" : 1671704466244,
            "value" : 65793
          }, {
            "startTime" : 1671704466244,
            "value" : 52399
          }, {
            "startTime" : 1671704466244,
            "value" : 53603
          }, {
            "startTime" : 1671704466244,
            "value" : 65137
          }, {
            "startTime" : 1671704466244,
            "value" : 45250
          }, {
            "startTime" : 1671704466244,
            "value" : 39848
          }, {
            "startTime" : 1671704466245,
            "value" : 40345
          }, {
            "startTime" : 1671704466245,
            "value" : 41282
          }, {
            "startTime" : 1671704466245,
            "value" : 45240
          }, {
            "startTime" : 1671704466245,
            "value" : 44933
          }, {
            "startTime" : 1671704466245,
            "value" : 49555
          }, {
            "startTime" : 1671704466245,
            "value" : 46230
          }, {
            "startTime" : 1671704466245,
            "value" : 41341
          }, {
            "startTime" : 1671704466245,
            "value" : 51553
          }, {
            "startTime" : 1671704466245,
            "value" : 48527
          }, {
            "startTime" : 1671704466245,
            "value" : 41555
          }, {
            "startTime" : 1671704466245,
            "value" : 43529
          }, {
            "startTime" : 1671704466245,
            "value" : 40576
          }, {
            "startTime" : 1671704466245,
            "value" : 44314
          }, {
            "startTime" : 1671704466245,
            "value" : 42209
          }, {
            "startTime" : 1671704466245,
            "value" : 42269
          }, {
            "startTime" : 1671704466245,
            "value" : 55181
          }, {
            "startTime" : 1671704466245,
            "value" : 46888
          }, {
            "startTime" : 1671704466246,
            "value" : 52124
          }, {
            "startTime" : 1671704466246,
            "value" : 48511
          }, {
            "startTime" : 1671704466246,
            "value" : 46079
          }, {
            "startTime" : 1671704466246,
            "value" : 43398
          }, {
            "startTime" : 1671704466246,
            "value" : 44977
          }, {
            "startTime" : 1671704466246,
            "value" : 44531
          }, {
            "startTime" : 1671704466246,
            "value" : 47373
          }, {
            "startTime" : 1671704466246,
            "value" : 49537
          }, {
            "startTime" : 1671704466246,
            "value" : 41857
          }, {
            "startTime" : 1671704466246,
            "value" : 45411
          }, {
            "startTime" : 1671704466246,
            "value" : 43677
          }, {
            "startTime" : 1671704466246,
            "value" : 46906
          }, {
            "startTime" : 1671704466246,
            "value" : 41530
          }, {
            "startTime" : 1671704466246,
            "value" : 41861
          }, {
            "startTime" : 1671704466246,
            "value" : 46001
          }, {
            "startTime" : 1671704466246,
            "value" : 44939
          }, {
            "startTime" : 1671704466246,
            "value" : 41721
          }, {
            "startTime" : 1671704466246,
            "value" : 40157
          }, {
            "startTime" : 1671704466247,
            "value" : 41353
          }, {
            "startTime" : 1671704466247,
            "value" : 47068
          }, {
            "startTime" : 1671704466247,
            "value" : 45441
          }, {
            "startTime" : 1671704466247,
            "value" : 46632
          }, {
            "startTime" : 1671704466247,
            "value" : 40109
          }, {
            "startTime" : 1671704466247,
            "value" : 45001
          }, {
            "startTime" : 1671704466247,
            "value" : 46052
          }, {
            "startTime" : 1671704466247,
            "value" : 39352
          }, {
            "startTime" : 1671704466247,
            "value" : 39759
          }, {
            "startTime" : 1671704466247,
            "value" : 40775
          }, {
            "startTime" : 1671704466247,
            "value" : 37440
          }, {
            "startTime" : 1671704466247,
            "value" : 43223
          }, {
            "startTime" : 1671704466247,
            "value" : 41111
          }, {
            "startTime" : 1671704466247,
            "value" : 44585
          }, {
            "startTime" : 1671704466247,
            "value" : 39322
          } ]
        }
      } ]
    } ]
  } ]
}